README.md
setup.cfg
setup.py
ioc_cli/__init__.py
ioc_cli/activate.py
ioc_cli/clone.py
ioc_cli/console.py
ioc_cli/create.py
ioc_cli/deactivate.py
ioc_cli/destroy.py
ioc_cli/exec.py
ioc_cli/export.py
ioc_cli/fetch.py
ioc_cli/fstab.py
ioc_cli/get.py
ioc_cli/import.py
ioc_cli/list.py
ioc_cli/migrate.py
ioc_cli/pkg.py
ioc_cli/promote.py
ioc_cli/provision.py
ioc_cli/rename.py
ioc_cli/restart.py
ioc_cli/set.py
ioc_cli/snapshot.py
ioc_cli/start.py
ioc_cli/stop.py
ioc_cli/update.py
ioc_cli.egg-info/PKG-INFO
ioc_cli.egg-info/SOURCES.txt
ioc_cli.egg-info/dependency_links.txt
ioc_cli.egg-info/entry_points.txt
ioc_cli.egg-info/requires.txt
ioc_cli.egg-info/top_level.txt
ioc_cli/shared/__init__.py
ioc_cli/shared/click.py
ioc_cli/shared/jail.py
ioc_cli/shared/output.py